timosbadlibraries/__init__.py
timosbadlibraries/RSAServer/RSA.py
timosbadlibraries/RSAServer/RSAServer.py
timosbadlibraries/RSAServer/__init__.py
timosbadlibraries-1.0.0.dist-info/LICENSE
timosbadlibraries-1.0.0.dist-info/METADATA
timosbadlibraries-1.0.0.dist-info/WHEEL
timosbadlibraries-1.0.0.dist-info/top_level.txt
timosbadlibraries-1.0.0.dist-info/RECORD
