Metadata-Version: 2.1
Name: timosbadlibraries
Version: 1.0.0
Summary: A package to demonstrate vulnerable implementations
Author-email: pauvretimo <timo@grossepout.re>
Project-URL: Homepage, https://github.com/timo-s-projects/timosbadlibraries
Project-URL: Issues, https://github.com/timo-s-projects/timosbadlibraries/issues
Keywords: cybersecurity,educational,bad implementation,rsa
Classifier: Programming Language :: Python :: 3
Classifier: License :: OSI Approved :: MIT License
Classifier: Operating System :: OS Independent
Classifier: Topic :: Security
Classifier: Topic :: Security :: Cryptography
Requires-Python: >=3.10
License-File: LICENSE
Requires-Dist: numpy
Requires-Dist: pycryptodome
